flet_like_streamlit/__init__.py
flet_like_streamlit/control.py
flet_like_streamlit/main.py
flet_like_streamlit-0.0.8.dist-info/LICENSE
flet_like_streamlit-0.0.8.dist-info/METADATA
flet_like_streamlit-0.0.8.dist-info/WHEEL
flet_like_streamlit-0.0.8.dist-info/entry_points.txt
flet_like_streamlit-0.0.8.dist-info/top_level.txt
flet_like_streamlit-0.0.8.dist-info/RECORD
