Metadata-Version: 2.1
Name: flet-like-streamlit
Version: 0.0.8
Summary: Flet working like streamlit
Home-page: https://github.com/Shogo0607/flet-like-streamlit
Author: Omochi
Author-email: soffionam@yahoo.co.jp
Classifier: Programming Language :: Python :: 3.7
Classifier: License :: OSI Approved :: MIT License
Classifier: Operating System :: OS Independent
License-File: LICENSE
Requires-Dist: flet
Requires-Dist: numpy
Requires-Dist: pandas
